aio_api_ros/__init__.py
aio_api_ros/connection.py
aio_api_ros/creators.py
aio_api_ros/errors.py
aio_api_ros/parser.py
aio_api_ros/simple_pool.py
aio_api_ros/unpacker.py
aio_api_ros-0.0.19.dist-info/LICENSE
aio_api_ros-0.0.19.dist-info/METADATA
aio_api_ros-0.0.19.dist-info/WHEEL
aio_api_ros-0.0.19.dist-info/top_level.txt
aio_api_ros-0.0.19.dist-info/RECORD
