Metadata-Version: 2.1
Name: aio-api-ros
Version: 0.0.19
Summary: async implementation Mikrotik api
Home-page: https://github.com/frostspb/aio_api_ros
Author: Frostspb
Author-email: UNKNOWN
License: MIT
Keywords: mikrotik,asyncio,apiRos
Platform: UNKNOWN
Classifier: Development Status :: 3 - Alpha
Classifier: Programming Language :: Python :: 3.5
Classifier: Programming Language :: Python :: 3.6
Classifier: Programming Language :: Python :: 3.7
